accrete_temp00/.DS_Store
accrete_temp00/__init__.py
accrete_temp00/dataclass.py
accrete_temp00-0.1.1.dist-info/METADATA
accrete_temp00-0.1.1.dist-info/WHEEL
accrete_temp00-0.1.1.dist-info/RECORD
