Metadata-Version: 2.1
Name: accrete_temp00
Version: 0.1.1
Summary: dataclass
Author: Your Name
Author-email: you@example.com
Requires-Python: >=3.12.5,<4.0.0
Classifier: Programming Language :: Python :: 3
Requires-Dist: pandera[io] (>=0.20.4,<0.21.0)
